{
	"type": "divinerpg:highest_ground",
	"biomes": "#divinerpg:is_iceika",
	"step": "surface_structures",
	"spawn_overrides": {
    "monster": {
      "bounding_box": "full",
      "spawns": [
        {
          "type": "divinerpg:workshop_tinkerer",
          "weight": 1,
          "minCount": 1,
          "maxCount": 1
        },
        {
          "type": "divinerpg:workshop_merchant",
          "weight": 1,
          "minCount": 1,
          "maxCount": 1
        }
      ]
     }
	},
	"terrain_adaptation": "beard_thin",
	"start_pool": "divinerpg:iceika/iceika_houses",
	"size": 6,
	"min_height": 64,
	"max_height": 250,
	"bury": 0,
	"max_distance_from_center": 1
}