{
  "parent": "minecraft:recipes/root",
  "criteria": {
    "has_twilight_stone": {
      "conditions": {
        "items": [
          {
            "items": [
              "divinerpg:twilight_stone"
            ]
          }
        ]
      },
      "trigger": "minecraft:inventory_changed"
    },
    "has_the_recipe": {
      "conditions": {
        "recipe": "divinerpg:shaped/milk_stone"
      },
      "trigger": "minecraft:recipe_unlocked"
    }
  },
  "requirements": [
    [
      "has_twilight_stone",
      "has_the_recipe"
    ]
  ],
  "rewards": {
    "recipes": [
      "divinerpg:shaped/milk_stone"
    ]
  }
}