{
  "display":{
    "icon":{
      "item":"divinerpg:arksiane_lump"
    },
    "title":{
      "translate":"advancement.divinerpg.vethea.unlimited_power"
    },
    "frame":"challenge",
    "description":{
      "translate":"advancement.divinerpg.vethea.unlimited_power.desc"
    },
    "announce_to_chat":true
  },
  "parent":"divinerpg:vethea/swiss_cheese",
  "criteria":{
    "kill_wreck":{
      "trigger":"minecraft:player_killed_entity",
      "conditions":{
        "entity":{
          "type":"divinerpg:wreck"
        }
      }
    }
  }
}
